linqex/__init__.py
linqex/utils.py
linqex/enumerable/__init__.py
linqex/enumerable/iterdict.py
linqex/enumerable/iteritem.py
linqex/enumerable/iterlist.py
linqex/tools/__init__.py
linqex/tools/iterdicttool.py
linqex/tools/iteritemtool.py
linqex/tools/iterlisttool.py
linqex-1.6.3.dist-info/LICENSE
linqex-1.6.3.dist-info/METADATA
linqex-1.6.3.dist-info/WHEEL
linqex-1.6.3.dist-info/top_level.txt
linqex-1.6.3.dist-info/RECORD
