Metadata-Version: 2.1
Name: linqex
Version: 1.6.3
Summary: The linq module in C# has been adapted for python with some modifications.
Home-page: https://github.com/TahsinCr/python-linqex
Author: TahsinCr
Author-email: TahsinCr@outlook.com
License: MIT
Keywords: linq,linqex,ex,enumerable
Classifier: Programming Language :: Python :: 3
Classifier: License :: OSI Approved :: MIT License
Classifier: Operating System :: OS Independent
Requires-Python: >=3
License-File: LICENSE
